src/__init__.py
src/main.py
lookandcris_hello-0.2.dist-info/LICENSE
lookandcris_hello-0.2.dist-info/METADATA
lookandcris_hello-0.2.dist-info/WHEEL
lookandcris_hello-0.2.dist-info/entry_points.txt
lookandcris_hello-0.2.dist-info/top_level.txt
lookandcris_hello-0.2.dist-info/RECORD
