Metadata-Version: 2.1
Name: lookandcris_hello
Version: 0.2
Summary: A small example package with some dependencies
Author: LookAndCris
License: MIT
License-File: LICENSE
